{
  "timestamp": 1770507894.1808977,
  "scan_id": "1770507894",
  "safety": {
    "safety_flags": [
      {
        "signal": "Bot-like phrasing or rhythm",
        "confidence": 0.6,
        "evidence": "The phrase 'shoop da woop' is a repetitive internet meme, which could indicate automated or inorganic content generation.",
        "benign_explanation": "The user could be referencing a well-known internet meme as a form of humor or cultural reference."
      }
    ],
    "overall_risk": "low"
  },
  "cognitive": {
    "logical_fallacies": [],
    "cognitive_biases": [],
    "epistemic_uncertainty": 0.9
  },
  "localization": {
    "locality": "agnostic",
    "dialect_markers": [],
    "confidence": 0.3,
    "suggested_vibe": "internet meme"
  },
  "sovereign_local": {
    "local_findings": [],
    "overall_risk_score": 0.1,
    "engine": "SOVEREIGN_LOCAL_V1"
  }
}